[
    {
        "accountentityid": "20_123456789",
        "category": [
            {
                "coding": [
                    {
                        "code": "social-history",
                        "display": "Social History",
                        "system": "http://terminology.hl7.org/CodeSystem/observation-category"
                    }
                ],
                "text": "Social History"
            }
        ],
        "code": {
            "coding": [
                {
                    "code": "72166-2",
                    "display": "Tobacco smoking status",
                    "system": "http://loinc.org"
                },
                {
                    "code": "365980008",
                    "display": "Finding of tobacco use and exposure (finding)",
                    "system": "http://snomed.info/sct"
                }
            ],
            "text": "Smoking History"
        },
        "createddate": 1545982874465,
        "entityid": "20_123456789_eLxXMV4.zQ160sieYE6keeEbYrnagweZTOaVN.2G5i.t2QJOLFshAzdpP1g3uydoP3",
        "id": "eLxXMV4.zQ160sieYE6keeEbYrnagweZTOaVN.2G5i.t2QJOLFshAzdpP1g3uydoP3",
        "issued": "2021-08-05T05:00:00Z",
        "status": "final",
        "subject": {
            "display": "McGinnis, Warren James III",
            "reference": "Patient/e0w0LEDCYtfckT6N.CkJKCw3"
        },
        "valuecodeableconcept": {
            "coding": [
                {
                    "code": "266927001",
                    "display": "Tobacco smoking consumption unknown",
                    "system": "http://snomed.info/sct"
                }
            ],
            "text": "Never Assessed"
        }
    }
]