[
    {
        "accountentityid": "35_10086203",
        "accountid": 10086203,
        "amount": 59.1,
        "currency": "USD",
        "basetype": "CREDIT",
        "category": "Superannuation",
        "categoryid": 41,
        "categorysource": "SYSTEM",
        "categorytype": "DEFERRED_COMPENSATION",
        "originalref": "Vanguard Inflation Protected Securities Fund - CONTRIBUTION",
        "highlevelcategoryid": 10000016,
        "entityid": "35_10086203_11090705",
        "id": "11090705",
        "ismanual": false,
        "priceamount": 12.81,
        "pricecurrency": "USD",
        "quantity": 4.6136,
        "status": "POSTED",
        "sourceid": "65542897",
        "sourcetype": "AGGREGATED",
        "symbol": "VIPSX",
        "createddate": 1555286400000,
        "transactiondate": 1555286400000,
        "type": "401K_CONTRIBUTION"
    },
    {
        "accountentityid": "35_10086203",
        "accountid": 10086203,
        "amount": 70.92,
        "currency": "USD",
        "basetype": "CREDIT",
        "category": "Superannuation",
        "categoryid": 41,
        "categorysource": "SYSTEM",
        "categorytype": "DEFERRED_COMPENSATION",
        "originalref": "Vanguard Target Retirement XXXX Fund - CONTRIBUTION",
        "highlevelcategoryid": 10000016,
        "entityid": "35_10086203_11090704",
        "id": "11090704",
        "ismanual": false,
        "priceamount": 31.23,
        "pricecurrency": "USD",
        "quantity": 2.2709,
        "status": "POSTED",
        "sourceid": "35932344",
        "sourcetype": "AGGREGATED",
        "symbol": "VTWNX",
        "createddate": 1555286400000,
        "transactiondate": 1555286400000,
        "type": "401K_CONTRIBUTION"
    },
    {
        "accountentityid": "35_10086203",
        "accountid": 10086203,
        "amount": 106.38,
        "currency": "USD",
        "basetype": "CREDIT",
        "category": "Superannuation",
        "categoryid": 41,
        "categorysource": "SYSTEM",
        "categorytype": "DEFERRED_COMPENSATION",
        "originalref": "Vanguard Target Retirement Income Fund - CONTRIBUTION",
        "highlevelcategoryid": 10000016,
        "entityid": "35_10086203_11090703",
        "id": "11090703",
        "ismanual": false,
        "priceamount": 13.48,
        "pricecurrency": "USD",
        "quantity": 7.8917,
        "status": "POSTED",
        "sourceid": "74427632",
        "sourcetype": "AGGREGATED",
        "symbol": "VTINX",
        "createddate": 1555286400000,
        "transactiondate": 1555286400000,
        "type": "401K_CONTRIBUTION"
    },
    {
        "accountentityid": "35_10086203",
        "accountid": 10086203,
        "amount": 147.75,
        "currency": "USD",
        "basetype": "CREDIT",
        "category": "Superannuation",
        "categoryid": 41,
        "categorysource": "SYSTEM",
        "categorytype": "DEFERRED_COMPENSATION",
        "originalref": "Fidelity Freedom XXXX Fund - CONTRIBUTION",
        "highlevelcategoryid": 10000016,
        "entityid": "35_10086203_11090702",
        "id": "11090702",
        "ismanual": false,
        "priceamount": 11.78,
        "pricecurrency": "USD",
        "quantity": 12.5424,
        "status": "POSTED",
        "sourceid": "19142501",
        "sourcetype": "AGGREGATED",
        "symbol": "FFFHX",
        "createddate": 1555286400000,
        "transactiondate": 1555286400000,
        "type": "401K_CONTRIBUTION"
    },
    {
        "accountentityid": "35_10086203",
        "accountid": 10086203,
        "amount": 206.85,
        "currency": "USD",
        "basetype": "CREDIT",
        "category": "Superannuation",
        "categoryid": 41,
        "categorysource": "SYSTEM",
        "categorytype": "DEFERRED_COMPENSATION",
        "originalref": "Fidelity Diversified International Fund - CONTRIBUTION",
        "highlevelcategoryid": 10000016,
        "entityid": "35_10086203_11090701",
        "id": "11090701",
        "ismanual": false,
        "priceamount": 36.17,
        "pricecurrency": "USD",
        "quantity": 5.7188,
        "status": "POSTED",
        "sourceid": "61355684",
        "sourcetype": "AGGREGATED",
        "symbol": "FDIVX",
        "createddate": 1555286400000,
        "transactiondate": 1555286400000,
        "type": "401K_CONTRIBUTION"
    },
    {
        "accountentityid": "35_10086203",
        "accountid": 10086203,
        "amount": 59.1,
        "currency": "USD",
        "basetype": "CREDIT",
        "category": "Superannuation",
        "categoryid": 41,
        "categorysource": "SYSTEM",
        "categorytype": "DEFERRED_COMPENSATION",
        "originalref": "Vanguard Inflation Protected Securities Fund - CONTRIBUTION",
        "highlevelcategoryid": 10000016,
        "entityid": "35_10086203_11090710",
        "id": "11090710",
        "ismanual": false,
        "priceamount": 12.86,
        "pricecurrency": "USD",
        "quantity": 4.5956,
        "status": "POSTED",
        "sourceid": "46115445",
        "sourcetype": "AGGREGATED",
        "symbol": "VIPSX",
        "createddate": 1554076800000,
        "transactiondate": 1554076800000,
        "type": "401K_CONTRIBUTION"
    },
    {
        "accountentityid": "35_10086203",
        "accountid": 10086203,
        "amount": 70.92,
        "currency": "USD",
        "basetype": "CREDIT",
        "category": "Superannuation",
        "categoryid": 41,
        "categorysource": "SYSTEM",
        "categorytype": "DEFERRED_COMPENSATION",
        "originalref": "Vanguard Target Retirement XXXX Fund - CONTRIBUTION",
        "highlevelcategoryid": 10000016,
        "entityid": "35_10086203_11090709",
        "id": "11090709",
        "ismanual": false,
        "priceamount": 30.87,
        "pricecurrency": "USD",
        "quantity": 2.2974,
        "status": "POSTED",
        "sourceid": "70931324",
        "sourcetype": "AGGREGATED",
        "symbol": "VTWNX",
        "createddate": 1554076800000,
        "transactiondate": 1554076800000,
        "type": "401K_CONTRIBUTION"
    },
    {
        "accountentityid": "35_10086203",
        "accountid": 10086203,
        "amount": 106.38,
        "currency": "USD",
        "basetype": "CREDIT",
        "category": "Superannuation",
        "categoryid": 41,
        "categorysource": "SYSTEM",
        "categorytype": "DEFERRED_COMPENSATION",
        "originalref": "Vanguard Target Retirement Income Fund - CONTRIBUTION",
        "highlevelcategoryid": 10000016,
        "entityid": "35_10086203_11090708",
        "id": "11090708",
        "ismanual": false,
        "priceamount": 13.4,
        "pricecurrency": "USD",
        "quantity": 7.9388,
        "status": "POSTED",
        "sourceid": "76279211",
        "sourcetype": "AGGREGATED",
        "symbol": "VTINX",
        "createddate": 1554076800000,
        "transactiondate": 1554076800000,
        "type": "401K_CONTRIBUTION"
    },
    {
        "accountentityid": "35_10086203",
        "accountid": 10086203,
        "amount": 147.75,
        "currency": "USD",
        "basetype": "CREDIT",
        "category": "Superannuation",
        "categoryid": 41,
        "categorysource": "SYSTEM",
        "categorytype": "DEFERRED_COMPENSATION",
        "originalref": "Fidelity Freedom XXXX Fund - CONTRIBUTION",
        "highlevelcategoryid": 10000016,
        "entityid": "35_10086203_11090707",
        "id": "11090707",
        "ismanual": false,
        "priceamount": 11.52,
        "pricecurrency": "USD",
        "quantity": 12.8255,
        "status": "POSTED",
        "sourceid": "24738132",
        "sourcetype": "AGGREGATED",
        "symbol": "FFFHX",
        "createddate": 1554076800000,
        "transactiondate": 1554076800000,
        "type": "401K_CONTRIBUTION"
    },
    {
        "accountentityid": "35_10086203",
        "accountid": 10086203,
        "amount": 206.85,
        "currency": "USD",
        "basetype": "CREDIT",
        "category": "Superannuation",
        "categoryid": 41,
        "categorysource": "SYSTEM",
        "categorytype": "DEFERRED_COMPENSATION",
        "originalref": "Fidelity Diversified International Fund - CONTRIBUTION",
        "highlevelcategoryid": 10000016,
        "entityid": "35_10086203_11090706",
        "id": "11090706",
        "ismanual": false,
        "priceamount": 35.21,
        "pricecurrency": "USD",
        "quantity": 5.8748,
        "status": "POSTED",
        "sourceid": "97563535",
        "sourcetype": "AGGREGATED",
        "symbol": "FDIVX",
        "createddate": 1554076800000,
        "transactiondate": 1554076800000,
        "type": "401K_CONTRIBUTION"
    }
]